{
  "_comment": "AGENTS.md §12 (drift watchlist) as enforced code — architecture-hardening.md R1. Every PERMITTED same-logic-in->=2-places duplicate in this repo is enumerated here with its copies (file + a regex that must still match there) and its lock (the fixture/generated-file/test that catches drift, or 'unlocked' when none exists yet). scripts/drift-check.mjs (just check-drift / just check) enforces: (a) every copy exists where claimed, (b) every declared lock file exists and lockStatus is consistent with whether locks are registered, (c) for entries with a 'scan' block, no NEW file outside the registered copies matches the concept's detection pattern. Registration friction is the feature — do not add entries for concepts that haven't actually drifted or burned us; do not delete an entry because its pattern is inconvenient, tighten the pattern instead.",
  "entries": [
    {
      "concept": "note-rules-ts-rust",
      "description": "Per-keystroke note rules (title/tag/preview/wikilink/image) — the ONE sanctioned TS mirror of the Rust note domain (AGENTS.md §4 M6/M7). Copies must stay bit-for-bit per tests/conformance/*.json.",
      "lockStatus": "locked",
      "copies": [
        {
          "location": "packages/editor/src/filename.ts",
          "pattern": "export function validateTitle"
        },
        {
          "location": "packages/editor/src/tags.ts",
          "pattern": "export function scanTags"
        },
        {
          "location": "packages/editor/src/preview.ts",
          "pattern": "export function makePreview"
        },
        {
          "location": "packages/editor/src/images.ts",
          "pattern": "export const IMAGE_EXTENSIONS"
        },
        {
          "location": "src/shared/note/wikilinks.ts",
          "pattern": "export function resolveWikilink"
        },
        {
          "location": "crates/futo-notes-core/src/files/filenames.rs",
          "pattern": "pub fn sanitize_title"
        },
        {
          "location": "crates/futo-notes-model/src/tags.rs",
          "pattern": "pub fn tag_regex_matches"
        },
        {
          "location": "crates/futo-notes-model/src/note.rs",
          "pattern": "pub fn make_preview"
        },
        {
          "location": "crates/futo-notes-model/src/wikilinks.rs",
          "pattern": "pub fn resolve_wikilink"
        }
      ],
      "locks": [
        {
          "path": "tests/conformance/filename.json",
          "kind": "fixture"
        },
        {
          "path": "tests/conformance/tags.json",
          "kind": "fixture"
        },
        {
          "path": "tests/conformance/preview.json",
          "kind": "fixture"
        },
        {
          "path": "tests/conformance/image.json",
          "kind": "fixture"
        },
        {
          "path": "tests/conformance/wikilinks.json",
          "kind": "fixture"
        },
        {
          "path": "tests/conformance/generate.mjs",
          "kind": "generator"
        },
        {
          "path": "crates/futo-notes-model/tests/conformance.rs",
          "kind": "test"
        }
      ]
    },
    {
      "concept": "validate-server-url",
      "description": "Sync server URL validation, hand-written x3 (no Rust side). TS reads the full shared fixture; Kotlin hand-mirrors 5 of the 9 fixture cases inline (partial); Swift has no test at all — there is no iOS unit test target yet (AGENTS.md §12: 'the Swift copy has no automated fixture check').",
      "lockStatus": "partial",
      "note": "PARTIAL: TS is fully locked against the fixture. Kotlin's SyncManagerDefaultsTest.kt hand-mirrors a 5-case subset instead of reading server-url.json (L1-5 plan: make it read the full fixture). Swift is genuinely UNLOCKED pending an iOS test target (L1-4).",
      "copies": [
        {
          "location": "src/features/sync/syncServiceE2ee.ts",
          "pattern": "function validateSyncServerUrl"
        },
        {
          "location": "apps/android/app/src/main/java/com/futo/notes/SyncManager.kt",
          "pattern": "fun validateServerUrl"
        },
        {
          "location": "apps/ios/Sources/SyncManager.swift",
          "pattern": "func validateServerURL"
        }
      ],
      "locks": [
        {
          "path": "tests/conformance/server-url.json",
          "kind": "fixture"
        },
        {
          "path": "src/features/sync/syncServiceE2ee.test.ts",
          "kind": "test"
        },
        {
          "path": "apps/android/app/src/test/java/com/futo/notes/SyncManagerDefaultsTest.kt",
          "kind": "test"
        }
      ],
      "scan": {
        "dirs": ["src", "apps/ios/Sources", "apps/android/app/src/main"],
        "extensions": [".ts", ".swift", ".kt"],
        "pattern": "(function validateSyncServerUrl|fun validateServerUrl|func validateServerURL)\\b"
      }
    },
    {
      "concept": "sort-tiebreaker-modified-id",
      "description": "Note sort order (modified desc, id asc), emitted canonically by the Rust store and repeated in the three shell caches so local edits can re-sort without a disk scan. No shared fixture currently locks the four copies.",
      "lockStatus": "unlocked",
      "copies": [
        {
          "location": "src/features/notes/notes.svelte.ts",
          "pattern": "right\\.modificationTime\\s*-\\s*left\\.modificationTime\\s*\\|\\|\\s*left\\.id\\.localeCompare\\(right\\.id\\)"
        },
        {
          "location": "crates/futo-notes-store/src/vault.rs",
          "pattern": "right\\s*\\.modified_ms\\s*\\.cmp\\(&left\\.modified_ms\\)"
        },
        {
          "location": "apps/ios/Sources/NotesStore.swift",
          "pattern": "func resortInPlace"
        },
        {
          "location": "apps/android/app/src/main/java/com/futo/notes/NotesStore.kt",
          "pattern": "compareByDescending<NoteItem>\\s*\\{\\s*it\\.modifiedMs\\s*\\}\\.thenBy\\s*\\{\\s*it\\.id\\s*\\}"
        }
      ]
    },
    {
      "concept": "notes-root-triplet",
      "description": "Dev/prod notes-root split (M3 CRITICAL): 3 independent copies by design. AGENTS.md §6 explicitly accepts this as a non-goal for unification — registered so it's visible, not to be locked or collapsed.",
      "lockStatus": "unlocked",
      "note": "Deliberately accepted duplication (M3 CRITICAL guard) per AGENTS.md §6 non-goals — do not attempt to unify or lock this; it is registered so the drift registry documents ALL permitted duplicates, including the ones that stay prose-only. CORRECTION to AGENTS.md §12: the Android copy is NOT in NotesStore.kt (that class only takes a resolved `notesRoot: File`) — the actual dev/prod guard lives in NotesStorage.kt's `deviceFolderName`, and Android's split works differently (a distinct DEVICE-mode folder name, 'FUTO Notes Dev' vs 'FUTO Notes', since its APP/INTERNAL modes already isolate via the `.dev` applicationId on package-scoped paths) rather than the desktop/iOS 'fake-notes' vs 'futo-notes' directory-name split.",
      "copies": [
        {
          "location": "apps/tauri/src-tauri/src/vault_location.rs",
          "pattern": "fake-notes"
        },
        {
          "location": "apps/ios/Sources/NotesStore.swift",
          "pattern": "fake-notes"
        },
        {
          "location": "apps/android/app/src/main/java/com/futo/notes/NotesStorage.kt",
          "pattern": "FUTO Notes Dev"
        }
      ]
    },
    {
      "concept": "watcher-suppression-window",
      "description": "5s filesystem-watcher self-write suppression window: Rust const + TS write-suppression TTL literals. Locked via PKT-7's constants.json gate (F21).",
      "lockStatus": "locked",
      "copies": [
        {
          "location": "apps/tauri/src-tauri/src/filesystem_watcher.rs",
          "pattern": "const SUPPRESSION_WINDOW_MS"
        },
        {
          "location": "src/lib/platform/writeSuppression.ts",
          "pattern": "LOCAL_WRITE_TTL_MS|SYNC_WRITE_TTL_MS"
        }
      ],
      "locks": [
        {
          "path": "tests/conformance/constants.json",
          "kind": "fixture"
        },
        {
          "path": "src/lib/constantsConformance.test.ts",
          "kind": "test"
        }
      ]
    },
    {
      "concept": "path-safety-pair",
      "description": "Safe note-ID validation at the TypeScript platform boundary and Rust note vault. Both consumers read tests/conformance/path-safety.json so acceptance cannot silently diverge.",
      "lockStatus": "locked",
      "copies": [
        {
          "location": "src/lib/platform/pathSafety.ts",
          "pattern": "export function ensureSafeNoteId"
        },
        {
          "location": "crates/futo-notes-core/src/files/paths.rs",
          "pattern": "pub fn safe_note_path"
        }
      ],
      "locks": [
        {
          "path": "tests/conformance/path-safety.json",
          "kind": "fixture"
        },
        {
          "path": "src/lib/platform/pathSafety.test.ts",
          "kind": "test"
        },
        {
          "path": "crates/futo-notes-core/tests/path_safety_conformance.rs",
          "kind": "test"
        }
      ]
    },
    {
      "concept": "unique-id-collision-loop",
      "description": "The '-2, -3, ...' unique-id suffix resolver. Rust is canonical for desktop and native. The only TS copy is the browser-only development/test note-store harness. Separate tests protect each implementation; no shared fixture currently locks them.",
      "lockStatus": "unlocked",
      "copies": [
        {
          "location": "src/lib/localNoteStore.ts",
          "pattern": "private unique\\(wanted"
        },
        {
          "location": "crates/futo-notes-store/src/paths.rs",
          "pattern": "pub\\(crate\\) fn unique_note_id"
        }
      ]
    },
    {
      "concept": "title-validation-constants",
      "description": "MAX_TITLE_LENGTH (200) and the forbidden-character set, defined canonically in packages/editor/src/filename.ts + mirrored in Rust, and additionally hand-copied (as a live-input-filter fast path) in both native shells. The numeric 200 is locked cross-language via constants.json (TS+Rust only); the native hand-copies of both the number and the forbidden-char set are unlocked.",
      "lockStatus": "partial",
      "note": "PARTIAL: constants.json + constantsConformance.test.ts + conformance.rs lock maxTitleLength=200 for TS and Rust. NoteEditorScreen.kt's TITLE_MAX_LENGTH/FORBIDDEN_TITLE_CHARS and NoteEditorView.swift's titleMaxLength/forbiddenTitleScalars are UNLOCKED hand-copies (comment-only cross-reference, no test).",
      "copies": [
        {
          "location": "packages/editor/src/filename.ts",
          "pattern": "export const MAX_TITLE_LENGTH = 200"
        },
        {
          "location": "crates/futo-notes-core/src/files/filenames.rs",
          "pattern": "pub const MAX_TITLE_LENGTH: usize = 200"
        },
        {
          "location": "apps/android/app/src/main/java/com/futo/notes/ui/NoteEditorScreen.kt",
          "pattern": "private const val TITLE_MAX_LENGTH = 200"
        },
        {
          "location": "apps/ios/Sources/NoteEditorView.swift",
          "pattern": "private let titleMaxLength = 200"
        }
      ],
      "locks": [
        {
          "path": "tests/conformance/constants.json",
          "kind": "fixture"
        },
        {
          "path": "src/lib/constantsConformance.test.ts",
          "kind": "test"
        }
      ],
      "scan": {
        "dirs": ["packages/editor/src", "crates", "apps/ios/Sources", "apps/android/app/src/main"],
        "extensions": [".ts", ".rs", ".swift", ".kt"],
        "pattern": "MAX_TITLE_LENGTH\\s*[:=]\\s*(usize\\s*=\\s*)?200|TITLE_MAX_LENGTH\\s*=\\s*200|titleMaxLength\\s*=\\s*200"
      }
    }
  ]
}
